hypothesis_crosshair-0.0.25.dist-info/licenses/LICENSE
hypothesis_crosshair_provider/__init__.py
hypothesis_crosshair_provider/crosshair_provider.py
hypothesis_crosshair_provider/crosshair_provider_test.py
hypothesis_crosshair_provider/end_to_end_test.py
hypothesis_crosshair-0.0.25.dist-info/METADATA
hypothesis_crosshair-0.0.25.dist-info/WHEEL
hypothesis_crosshair-0.0.25.dist-info/entry_points.txt
hypothesis_crosshair-0.0.25.dist-info/top_level.txt
hypothesis_crosshair-0.0.25.dist-info/RECORD
