Metadata-Version: 2.4
Name: hypothesis-crosshair
Version: 0.0.25
Summary: Level-up your Hypothesis tests with CrossHair.
Author-email: Phillip Schanely <pschanely+B9vk@gmail.com>
License: MIT License
Project-URL: Homepage, https://github.com/pschanely/hypothesis-crosshair
Classifier: Development Status :: 2 - Pre-Alpha
Classifier: Framework :: Hypothesis
Classifier: Intended Audience :: Developers
Classifier: License :: OSI Approved :: MIT License
Classifier: Operating System :: OS Independent
Classifier: Programming Language :: Python
Classifier: Programming Language :: Python :: 3
Classifier: Programming Language :: Python :: 3.8
Classifier: Programming Language :: Python :: 3.9
Classifier: Programming Language :: Python :: 3.10
Classifier: Programming Language :: Python :: 3.11
Classifier: Programming Language :: Python :: 3.12
Classifier: Programming Language :: Python :: 3.13
Classifier: Topic :: Software Development :: Testing
Requires-Python: >=3.9
License-File: LICENSE
Requires-Dist: hypothesis>=6.137.0
Requires-Dist: crosshair-tool>=0.0.74
Dynamic: license-file
